[
    {
      "_id": 1,
        "active": true,
      "type": "anime",
      "title": "Neon Genesis Evangelion",
      "rating": 8.5,
      "date": "4th October 1995",
      "genre": ["Mecha", "Psychological", "Drama"],
      "mainCast": ["Shinji Ikari", "Rei Ayanami", "Asuka Langley Soryu"],
      "image": "posters/neon_genesis_evangelion.jpg",
      "numberOfSeasons": 1,
      "trailer": "https://www.youtube.com/embed/13nSISwxrY4",
      "description": "Teenagers piloting giant mechs must protect Earth from mysterious beings known as Angels while dealing with their own psychological struggles."
      },
      {
        "_id": 2,
        "active": false,
        "type": "kdrama",
        "title": "Crash Landing on You",
        "rating": 8.5,
        "date": "14th December 2019",
        "genre": ["Romance", "Drama", "Comedy"],
        "mainCast": ["Yoon Se-ri", "Ri Jeong-hyeok"],
        "image": "posters/crash_landing_on_you.jpg",
        "numberOfSeasons": 1,
        "trailer": "https://www.youtube.com/embed/GVQGWgeVc4k",
        "description": "A South Korean heiress crash-lands in North Korea while paragliding and comes into contact with a North Korean army officer, leading to a series of unexpected events and a cross-border romance."
      },
      {
        "_id": 3,
        "active": false,
        "type": "anime",
        "title": "One Punch Man",
        "rating": 8.7,
        "date": "5th October 2015",
        "genre": ["Action", "Comedy", "Superhero"],
        "mainCast": ["Saitama", "Genos", "Mumen Rider"],
        "image": "posters/one_punch_man.jpg",
        "numberOfSeasons": 2,
        "trailer": "https://www.youtube.com/embed/Poo5lqoWSGw",
        "description": "Saitama, a hero who can defeat any opponent with a single punch, seeks a worthy challenge to alleviate his boredom."
      },
      {
        "_id": 4,
        "active": false,
        "type": "kdrama",
        "title": "Itaewon Class",
        "rating": 8.8,
        "date": " 31st January 2020",
        "genre": ["Drama", "Romance"],
        "mainCast": ["Park Saeroyi", "Jo Yi-seo", "Oh Soo-ah"],
        "image": "posters/itaewon_class.jpg",
        "numberOfSeasons": 1,
        "trailer": "https://www.youtube.com/embed/NNP8m3gaaFE",
        "description": "An ex-convict and his friends strive to make their bar in Itaewon a success while dealing with various challenges and personal growth."
      },
      {
        "_id": 5,
        "active": false,
        "type": "anime",
        "title": "My Hero Academia",
        "rating": 8.4,
        "date": "3rd April 2016",
        "genre": ["Action", "Superpower", "School"],
        "mainCast": ["Izuku Midoriya", "Katsuki Bakugo", "All Might"],
        "image": "posters/my_hero_academia.jpg",
        "numberOfSeasons": 6,
        "trailer": "https://www.youtube.com/embed/EPVkcwyLQQ8",
        "description": "In a world where people have superpowers known as Quirks, Izuku Midoriya strives to become a hero despite being born without a Quirk."
      },
      {
        "_id": 6,
        "active": false,
        "type": "kdrama",
        "title": "Vincenzo",
        "rating": 9.1,
        "date": "20th February 2021",
        "genre": ["Crime", "Comedy", "Romance"],
        "mainCast": ["Vincenzo Cassano", "Hong Cha-young", "Jang Joon-woo"],
        "image": "posters/vincenzo.jpg",
        "numberOfSeasons": 1,
        "trailer": "https://www.youtube.com/embed/_J8tYxYB_YU",
        "description": "A lawyer with a Mafia background, Vincenzo Cassano, seeks justice in his own way while getting entangled in the complex world of South Korean corporate corruption."
      },
      {
        "_id": 7,
        "active": false,
        "type": "anime",
        "title": "Death Note",
        "rating": 9.1,
        "date": "4th October 2006",
        "genre": ["Mystery", "Psychological", "Thriller"],
        "mainCast": ["Light Yagami", "L", "Ryuk"],
        "image": "posters/death_note.jpg",
        "numberOfSeasons": 1,
        "trailer": "https://www.youtube.com/embed/tJZtOrm-WPk",
        "description": "A high school student discovers a mysterious notebook that allows him to kill anyone whose name he writes in it, leading to a cat-and-mouse game with a genius detective."
    },
    {
      "_id": 8,
      "active": false,
      "type": "anime",
      "title": "Demon Slayer",
      "rating": 8.7,
      "date": "6th April 2019",
      "genre": ["Action", "Supernatural", "Historical"],
      "mainCast": ["Tanjiro Kamado", "Nezuko Kamado", "Zenitsu Agatsuma"],
      "image": "posters/demon_slayer.jpg",
      "numberOfSeasons": 2,
      "trailer": "https://www.youtube.com/embed/VQGCKyvzIM4",
      "description": "After his family is slaughtered by demons and his sister turned into one, Tanjiro Kamado becomes a demon slayer to avenge his family and save his sister."
    },
    {
        "_id": 9,
        "active": false,
      "type": "anime",
      "title": "Cowboy Bebop",
      "rating": 8.9,
      "date": "3rd April 1998",
      "genre": ["Action", "Sci-Fi", "Space"],
      "mainCast": ["Spike Spiegel", "Jet Black", "Faye Valentine"],
      "image": "posters/cowboy_bebop.jpg",
      "numberOfSeasons": 1,
      "trailer": "https://www.youtube.com/embed/AJKEXDKBVdk",
      "description": "Bounty hunter Spike Spiegel and his eclectic crew travel the galaxy in pursuit of the galaxy's most dangerous criminals."
    },
    {
        "_id": 10,
        "active": false,
      "type": "anime",
      "title": "Hunter x Hunter",
      "rating": 9.1,
      "date": "2nd October 2011",
      "genre": ["Action", "Adventure", "Fantasy"],
      "mainCast": ["Gon Freecss", "Killua Zoldyck", "Kurapika"],
      "image": "posters/hunter_x_hunter.jpg",
      "numberOfSeasons": 6,
      "trailer": "https://www.youtube.com/embed/d6kBeJjTGnY",
      "description": "Gon Freecss aspires to become a Hunter to find his missing father and discover the world's secrets."
    },
    {
      "_id": 11,
        "active": false,
        "type": "anime",
        "title": "Attack on Titan",
        "rating": 9.0,
        "date": "6th April 2013",
        "genre": ["Action", "Fantasy", "Drama"],
        "mainCast": ["Eren Yeager", "Mikasa Ackerman", "Armin Arlert"],
        "image": "posters/attack_on_titan.jpg",
        "numberOfSeasons": 4,
        "trailer": "https://www.youtube.com/embed/MGRm4IzK1SQ",
        "description": "In a world where humanity resides within enormous walled cities to protect themselves from Titans, gigantic humanoid creatures, the story follows Eren Yeager and his friends who join the military to fight the Titans."
    },
    {
        "_id": 12,
        "active": false,
      "type": "kdrama",
      "title": "What's Wrong with Secretary Kim",
      "rating": 8.9,
      "date": "6th June 2018",
      "genre": ["Romance", "Comedy"],
      "mainCast": ["Lee Young-joon", "Kim Mi-so"],
      "image": "posters/whats_wrong_with_secretary_kim.jpg",
      "numberOfSeasons": 1,
      "trailer": "https://www.youtube.com/embed/e43gG2nC8Cg",
      "description": "A self-absorbed vice chairman and his capable secretary navigate their changing relationship as she decides to resign after working for him for nine years."
    },
    {
        "_id": 13,
        "active": false,
      "type": "kdrama",
      "title": "Moon Lovers: Scarlet Heart Ryeo",
      "rating": 8.5,
      "date": " 29th August 2016",
      "genre": ["Historical", "Romance", "Fantasy"],
      "mainCast": ["Hae Soo", "Wang So", "Wang Wook"],
      "image": "posters/moon_lovers.jpg",
      "numberOfSeasons": 1,
      "trailer": "https://www.youtube.com/embed/2ljxyaAIphc",
      "description": "A modern-day woman is transported back in time to the Goryeo era and becomes entangled with the princes vying for the throne."
    },
    {
        "_id": 14,
        "active": false,
      "type": "kdrama",
      "title": "Goblin",
      "rating": 8.9,
      "date": "2nd December 2016",
      "genre": ["Fantasy", "Romance", "Drama"],
      "mainCast": ["Kim Shin", "Ji Eun-tak", "Wang Yeo"],
      "image": "posters/goblin.jpg",
      "numberOfSeasons": 1,
      "trailer": "https://www.youtube.com/embed/8AcNEVUzV4o",
      "description": "A goblin and his bride's fateful romance unfolds as they navigate the challenges set by the deities in their quest for redemption and love."
    },
    {
        "_id": 15,
        "active": false,
      "type": "kdrama",
      "title": "Descendants of the Sun",
      "rating": 8.3,
      "date": "24th February 2016",
      "genre": ["Romance", "Action", "Drama"],
      "mainCast": ["Yoo Si-jin", "Kang Mo-yeon", "Seo Dae-young"],
      "image": "posters/descendants_of_the_sun.jpg",
      "numberOfSeasons": 1,
      "trailer": "https://www.youtube.com/embed/wTGwjDqtfzQ",
      "description": "A love story between a soldier and a surgeon unfolds in a fictional war-torn country, exploring the challenges of duty and love."
    },
    {
        "_id": 16,
        "active": false,
      "type": "anime",
      "title": "Steins;Gate",
      "rating": 9.1,
      "date": "6th April 2011",
      "genre": ["Thriller", "Sci-Fi"],
      "mainCast": ["Rintarou Okabe", "Kurisu Makise", "Mayuri Shiina"],
      "image": "posters/steins_gate.jpg",
      "numberOfSeasons": 1,
      "trailer": "https://www.youtube.com/embed/uMYhjVwp0Fk",
      "description": "A self-proclaimed mad scientist discovers a way to send messages to the past, leading to unforeseen consequences and a thrilling adventure."
    },
    {
        "_id": 17,
        "active": false,
      "type": "anime",
      "title": "Code Geass: Lelouch of the Rebellion",
      "rating": 8.9,
      "date": "6th October 2006",
      "genre": ["Action", "Military", "Sci-Fi"],
      "mainCast": ["Lelouch Lamperouge", "C.C.", "Suzaku Kururugi"],
      "image": "posters/code_geass.jpg",
      "numberOfSeasons": 2,
      "trailer": "https://www.youtube.com/embed/v-AGjx0N24U",
      "description": "In an alternate future, Lelouch vi Britannia gains the power of Geass and leads a rebellion against the oppressive Britannian Empire."
    },
    {

      "_id": 18,
        "active": false,
      "type": "anime",
      "title": "Naruto",
      "rating": 8.6,
      "date": "3rd october 2002",
      "genre": ["Action", "Adventure", "Ninja"],
      "mainCast": ["Naruto Uzumaki", "Sasuke Uchiha", "Sakura Haruno"],
      "image": "posters/naruto.jpg",
      "numberOfSeasons": 5,
      "trailer": "https://www.youtube.com/embed/-G9BqkgZXRA",
      "description": "Naruto Uzumaki, an aspiring ninja, seeks recognition from his peers and dreams of becoming the Hokage, the leader of his village."
    },
    {
        "_id": 19,
        "active": false,
      "type": "anime",
      "title": "Haikyuu!!",
      "rating": 8.7,
      "date": "6th April 2014",
      "genre": ["Sports", "Comedy", "Drama"],
      "mainCast": ["Hinata Shoyo", "Kageyama Tobio", "Daichi Sawamura"],
      "image": "posters/haikyuu.jpg",
      "numberOfSeasons": 4,
      "trailer": "https://www.youtube.com/embed/JOGp2c7-cKc",
      "description": "Inspired by a small-statured player, a high school student joins the volleyball team and aims to become the best player in the sport."
    },
    {
        "_id": 20,
        "active": false,
      "type": "anime",
      "title": "Tokyo Ghoul",
      "rating": 8.3,
      "date": "4th July 2014",
      "genre": ["Action", "Horror", "Supernatural"],
      "mainCast": ["Ken Kaneki", "Touka Kirishima", "Haise Sasaki"],
      "image": "posters/tokyo_ghoul.jpg",
      "numberOfSeasons": 4,
      "trailer": "https://www.youtube.com/embed/UUeqpuZobBw",
      "description": "After a chance encounter with a flesh-eating ghoul, a college student undergoes a horrifying transformation and must navigate the dark and dangerous world of ghouls."
    },
    {
        "_id": 21,
        "active": false,
      "type": "kdrama",
      "title": "Mr. Sunshine",
      "rating": 8.8,
      "date": "7th July 2018",
      "genre": ["Historical", "Romance", "Drama"],
      "mainCast": ["Eugene Choi", "Ko Ae-shin", "Kim Hui-seong"],
      "image": "posters/mr_sunshine.jpg",
      "numberOfSeasons": 1,
      "trailer": "https://www.youtube.com/embed/rPJSo4fhtRU",
      "description": "A Korean-born American soldier returns to his homeland as a U.S. Marine officer and gets involved in the struggles and conflicts of the late Joseon era."
    },
    {
        "_id": 22,
        "active": false,
      "type": "kdrama",
      "title": "Hospital Playlist",
      "rating": 8.7,
      "date": "12th March 2020",
      "genre": ["Medical", "Drama", "Slice of Life"],
      "mainCast": ["Ik-jun", "Song-hwa", "Joon-wan"],
      "image": "posters/hospital_playlist.jpg",
      "numberOfSeasons": 2,
      "trailer": "https://www.youtube.com/embed/xqIM2cenBAs",
      "description": "Five doctors and long-time friends navigate the challenges of life and medicine as they work in the same hospital."
    },
    {
        "_id": 23,
        "active": false,
      "type": "kdrama",
      "title": "Reply 1988",
      "rating": 9.1,
      "date": "6th November 2015",
      "genre": ["Slice of Life", "Comedy", "Romance"],
      "mainCast": ["Sung Deok-sun", "Choi Taek", "Kim Jung-hwan"],
      "image": "posters/reply_1988.jpg",
      "numberOfSeasons": 1,
      "trailer": "https://www.youtube.com/embed/c-EMf3JdxUA",
      "description": "Set in the late 1980s, the drama follows the lives and relationships of five childhood friends living in the same neighborhood."
    },
    {
        "_id": 24,
        "active": false,
      "type": "kdrama",
      "title": "It's Okay to Not Be Okay",
      "rating": 8.8,
      "date": "20 June 2020",
      "genre": ["Psychological", "Romance", "Drama"],
      "mainCast": ["Moon Kang-tae", "Go Moon-young", "Nam Ju-ri"],
      "image": "posters/its_okay_to_not_be_okay.jpg",
      "numberOfSeasons": 1,
      "trailer": "https://www.youtube.com/embed/1H__LNPCc80",
      "description": "A psychiatric hospital caregiver and a popular children's book author with an antisocial personality disorder develop an unconventional romance."
    },
    {
        "_id": 25,
        "active": false,
        "type": "anime",
        "title": "Fullmetal Alchemist: Brotherhood",
        "rating": 9.1,
        "date": "5th April 2009",
        "genre": ["Action", "Adventure", "Fantasy"],
        "mainCast": ["Edward Elric", "Alphonse Elric", "Roy Mustang"],
        "image": "posters/fullmetal_alchemist.jpg",
        "numberOfSeasons": 1,
        "trailer": "https://www.youtube.com/embed/-GoNo0DGroU",
        "description": "In a world of alchemy, two brothers seek the Philosopher's Stone to restore their bodies after a failed alchemical experiment."
      },
      {
        "_id": 26,
        "active": false,
        "type": "kdrama",
        "title": "Kingdom",
        "rating": 8.6,
        "date": "25th January 2019",
        "genre": ["Action", "Horror", "Historical"],
        "mainCast": ["Crown Prince Lee Chang", "Seo-bi", "Jo Hak-jo"],
        "image": "posters/kingdom.jpg",
        "numberOfSeasons": 2,
        "trailer": "https://www.youtube.com/embed/4l-yByZpaaM",
        "description": "A prince investigates a mysterious plague that turns people into flesh-eating monsters, uncovering political conspiracies along the way."
      },
      {
        "_id": 27,
        "active": false,
        "type": "anime",
        "title": "Your Lie in April",
        "rating": 8.9,
        "date": "10th October 2014",
        "genre": ["Romance", "Music", "Drama"],
        "mainCast": ["Kosei Arima", "Kaori Miyazono", "Tsubaki Sawabe"],
        "image": "posters/your_lie_in_april.jpg",
        "numberOfSeasons": 1,
        "trailer": "https://www.youtube.com/embed/3aL0gDZtFbE",
        "description": "A talented pianist, traumatized by his mother's death, finds inspiration and love through a free-spirited violinist."
      },
      {
        "_id": 28,
        "active": false,
        "type": "anime",
        "title": "Sword Art Online",
        "rating": 7.6,
        "date": "7th July 2012",
        "genre": ["Action", "Adventure", "Fantasy"],
        "mainCast": ["Kirito", "Asuna", "Klein"],
        "image": "posters/sword_art_online.jpg",
        "numberOfSeasons": 4,
        "trailer": "https://www.youtube.com/embed/6ohYYtxfDCg",
        "description": "Players get trapped in a virtual reality MMORPG, where death in the game means death in real life, and must navigate the challenges to survive."
      },
      {
        "_id": 29,
        "active": false,
        "type": "kdrama",
        "title": "While You Were Sleeping",
        "rating": 8.7,
        "date": "27th September 2017",
        "genre": ["Fantasy", "Romance", "Thriller"],
        "mainCast": ["Nam Hong-joo", "Jung Jae-chan", "Han Woo-tak"],
        "image": "posters/while_you_were_sleeping.jpg",
        "numberOfSeasons": 1,
        "trailer": "https://www.youtube.com/embed/8_rEZV3n3mk",
        "description": "Three individuals with the ability to foresee future events become entangled in a web of fate, solving crimes and preventing tragedies."
      },
      {
        "_id": 30,
        "active": false,
        "type": "anime",
        "title": "One Piece",
        "rating": 8.7,
        "date": "20th October 1999",
        "genre": ["Action", "Adventure", "Fantasy"],
        "mainCast": ["Monkey D. Luffy", "Zoro", "Nami"],
        "image": "posters/one_piece.jpg",
        "numberOfSeasons": 20,
        "trailer": "https://www.youtube.com/embed/S8_YwFLCh4U",
        "description": "Follow Monkey D. Luffy and his diverse crew of pirates as they search for the ultimate treasure, the One Piece, in this epic adventure."
      },
      {
        "_id": 31,
        "active": false,
        "type": "kdrama",
        "title": "Start-Up",
        "rating": 8.6,
        "date": "17th October 2020",
        "genre": ["Romance", "Drama", "Comedy"],
        "mainCast": ["Seo Dal-mi", "Nam Do-san", "Han Ji-pyeong"],
        "image": "posters/start_up.jpg",
        "numberOfSeasons": 1,
        "trailer": "https://www.youtube.com/embed/BemKyzbLDDc",
        "description": "Aspiring entrepreneurs navigate the competitive world of startups, love, and friendship, pursuing their dreams in the tech industry."
      },
      {
        "_id": 32,
        "active": false,
        "type": "anime",
        "title": "Dragon Ball Z",
        "rating": 8.7,
        "date": "26th April 1989",
        "genre": ["Action", "Adventure", "Fantasy"],
        "mainCast": ["Goku", "Vegeta", "Gohan"],
        "image": "posters/dragon_ball_z.jpg",
        "numberOfSeasons": 9,
        "trailer": "https://www.youtube.com/embed/sxufB6DxXk0",
        "description": "Goku and his friends defend Earth against powerful foes and seek the magical Dragon Balls in this iconic anime series."
      },
      {
        "_id": 33,
        "active": false,
        "type": "kdrama",
        "title": "The King: Eternal Monarch",
        "rating": 8.7,
        "date": "17th April 2020",
        "genre": ["Fantasy", "Romance", "Thriller"],
        "mainCast": ["Lee Gon", "Jung Tae-eul", "Jo Eun-sup"],
        "image": "posters/the_king_eternal_monarch.jpg",
        "numberOfSeasons": 1,
        "trailer": "https://www.youtube.com/embed/jJwuFjmfjRY",
        "description": "A modern-day Korean emperor crosses into an alternate universe and becomes entangled in a political conspiracy and a love story."
      },
      {
        "_id": 34,
        "active": false,
        "type": "kdrama",
        "title": "Hotel Del Luna",
        "rating": 8.8,
        "date": "13th July 2019",
        "genre": ["Fantasy", "Romance", "Horror"],
        "mainCast": ["Jang Man-wol", "Goo Chan-sung", "Sanchez"],
        "image": "posters/hotel_del_luna.jpg",
        "numberOfSeasons": 1,
        "trailer": "https://www.youtube.com/embed/1IjMTR2DxlA",
        "description": "The owner of a supernatural hotel that caters to ghosts and spirits encounters a human guest who becomes her business partner, unraveling their intertwined fates."
      }


]
